kfk/__init__.py
kfk/client.py
kfk/consumer.py
kfk/main.py
kfk/producer.py
kfk_vvvvvvvvv-0.1.1.dist-info/METADATA
kfk_vvvvvvvvv-0.1.1.dist-info/WHEEL
kfk_vvvvvvvvv-0.1.1.dist-info/entry_points.txt
kfk_vvvvvvvvv-0.1.1.dist-info/top_level.txt
kfk_vvvvvvvvv-0.1.1.dist-info/RECORD
