Metadata-Version: 2.1
Name: kfk-vvvvvvvvv
Version: 0.1.1
Author: vova
Requires-Dist: kafka-python
Requires-Dist: rich
